bids_neuropoly/__init__.py
bids_neuropoly/bids.py
bids_neuropoly-0.2.dist-info/METADATA
bids_neuropoly-0.2.dist-info/WHEEL
bids_neuropoly-0.2.dist-info/top_level.txt
bids_neuropoly-0.2.dist-info/RECORD
