Metadata-Version: 2.1
Name: bids-neuropoly
Version: 0.2
Summary: An open-source BIDS parser.
Home-page: https://github.com/neuropoly/bids_neuropoly
Author: Christian S. Perone
Author-email: christian.perone@gmail.com
License: UNKNOWN
Platform: UNKNOWN
Classifier: Development Status :: 3 - Alpha
Classifier: Intended Audience :: Developers
Classifier: Programming Language :: Python :: 3
Requires-Dist: pybids (>=0.6.5)
Requires-Dist: nibabel (>=2.3.0)
Requires-Dist: pandas (>=0.23.0)
